loghandler/__init__.py
loghandler/app.py
loghandler/test.py
loghandler/core/__init__.py
loghandler/core/exceptions.py
loghandler/core/helpers.py
loghandler/modules/__init__.py
loghandler/modules/database.py
loghandler/modules/elasticsearch.py
loghandler/modules/stdout.py
loghandler-0.5.0.dist-info/LICENSE
loghandler-0.5.0.dist-info/METADATA
loghandler-0.5.0.dist-info/WHEEL
loghandler-0.5.0.dist-info/top_level.txt
loghandler-0.5.0.dist-info/RECORD
