Metadata-Version: 2.1
Name: loghandler
Version: 0.5.0
Summary: Python logging library with support for multiple destinations
Home-page: https://github.com/math280h/loghandler
Author: math280h
License: UNKNOWN
Platform: UNKNOWN
License-File: LICENSE
Requires-Dist: rich (==10.13.0)
Requires-Dist: requests (==2.26.0)
Requires-Dist: elasticsearch (==7.15.2)
Requires-Dist: SQLAlchemy (==1.4.27)
Requires-Dist: PyMySQL (==1.0.2)
Requires-Dist: psycopg2 (==2.9.2)
Requires-Dist: cryptography (==35.0.0)
